py_serial_rs-0.1.6.dist-info/METADATA
py_serial_rs-0.1.6.dist-info/WHEEL
py_serial_rs-0.1.6.dist-info/license_files/LICENSE
py_serial_rs.libs/libattr-4f2a9577.so.1
py_serial_rs.libs/libcap-79733b59.so.2
py_serial_rs.libs/libbz2-a273e504.so.1
py_serial_rs.libs/liblzma-004595ca.so.5
py_serial_rs.libs/libelf-3d9de92a.so.1
py_serial_rs.libs/libudev-8edd2273.so.1
py_serial_rs.libs/libdw-780627ce.so.1
py_serial_rs/__init__.py
py_serial_rs/py_serial_rs.cpython-37m-x86_64-linux-gnu.so
py_serial_rs-0.1.6.dist-info/RECORD
