Metadata-Version: 2.1
Name: py_serial_rs
Version: 0.1.6
Classifier: Programming Language :: Rust
Classifier: Programming Language :: Python :: Implementation :: CPython
Classifier: Programming Language :: Python :: Implementation :: PyPy
License-File: LICENSE
Summary: Read and write data over the serial ports
Author: Jürgen Hahn
Author-email: mail.jhahn@googlemail.com
Requires-Python: >=3.8
Project-URL: Source Code, https://github.com/jrhahn/py_serial_rs
Project-URL: Issues, https://github.com/jrhahn/py_serial_rs/issues
Project-URL: Documentation, https://py-serial-rs.readthedocs.io/en/latest/
